Day_6/rtl/pmu_fsm_icarus.sv
// ===================================================================
//  Power Management Unit ( with Sleep and OFF sequencing )
//  Author: Dhananjay Joshi
//  Description:
//  Simple FSM to implement a PMU block
//  handles power up, active and power down sequences
// ===================================================================

module pmu_fsm (
    input wire clk,
    input wire reset_n,

    // PMU Requests
    input wire req_idle, 
    input wire req_sleep, 
    input wire req_off, 
    input wire wake_up,

    // Status Inputs
    input wire pwr_stable,
    input wire clk_stable,
    input wire retention_ready,

    // Control outputs
    output reg clk_gate_en,
    output reg pwr_gate_en,
    output reg retention_en,
    output reg retention_save,
    output reg retention_restore,
    output reg [1:0] dvfs_ctrl,
    output reg reset_ctrl,
    output reg [1:0] pwr_state,
    output reg seq_busy,
    output reg error
);

// ===================================================================
// State Encoding - Binary for simplicity, easy to debug
// ===================================================================
localparam [2:0] ACTIVE    = 3'b000,
                 IDLE      = 3'b001,
                 SLEEP     = 3'b010,
                 OFF       = 3'b011,
                 SLEEP_ENT = 3'b100,
                 OFF_ENT   = 3'b101,
                 WAKE_UP   = 3'b110;

reg [2:0] curr_state, next_state;

// ===================================================================
// Sequential Elements
// ===================================================================
reg [7:0] seq_timer;

// Input synchronization (2-stage for simplicity)
reg [3:0] sync_stage1, sync_stage2;
wire req_idle_sync, req_sleep_sync, req_off_sync, wake_up_sync;

assign {req_idle_sync, req_sleep_sync, req_off_sync, wake_up_sync} = sync_stage2;

always @(posedge clk or negedge reset_n) begin
    if (!reset_n) begin
        sync_stage1 <= 4'b0;
        sync_stage2 <= 4'b0;
    end else begin
        sync_stage1 <= {req_idle, req_sleep, req_off, wake_up};
        sync_stage2 <= sync_stage1;
    end
end

// ===================================================================
// State Machine 
// ===================================================================

// State register
always @(posedge clk or negedge reset_n) begin
    if (!reset_n) begin 
        curr_state <= ACTIVE;
        seq_timer <= 8'h00;
    end else begin 
        curr_state <= next_state;
        
        // Timer control
        if (curr_state != next_state) begin
            seq_timer <= 8'h00;
        end else if (seq_busy) begin
            seq_timer <= seq_timer + 1'b1;
        end
    end
end

// Next state logic
always @(*) begin
    // Default values
    next_state = curr_state;
    seq_busy = 1'b0;
    error = 1'b0;

    case (curr_state)
        ACTIVE: begin
            // Check synchronized requests
            if (wake_up_sync) begin
                next_state = ACTIVE; // Stay in ACTIVE on wake_up
            end else if (req_off_sync) begin
                next_state = OFF_ENT;
            end else if (req_sleep_sync) begin
                next_state = SLEEP_ENT;
            end else if (req_idle_sync) begin
                next_state = IDLE;
            end
        end

        IDLE: begin
            if (wake_up_sync) begin
                next_state = ACTIVE;
            end else if (req_off_sync) begin
                next_state = OFF_ENT;
            end else if (req_sleep_sync) begin
                next_state = SLEEP_ENT;
            end
        end

        SLEEP: begin
            if (wake_up_sync) begin
                next_state = WAKE_UP;
            end else if (req_off_sync) begin
                next_state = OFF_ENT;
            end
        end

        OFF: begin
            if (wake_up_sync) begin
                next_state = WAKE_UP;
            end
        end

        SLEEP_ENT: begin
            seq_busy = 1'b1;
            if (seq_timer >= 8'h03) begin // Increased to 3 cycles
                if (retention_ready) begin
                    next_state = SLEEP;
                end else if (seq_timer >= 8'h0F) begin // Shorter timeout
                    next_state = ACTIVE;
                    error = 1'b1;
                end
            end
        end

        OFF_ENT: begin
            seq_busy = 1'b1;
            if (seq_timer >= 8'h05) begin
                next_state = OFF;
            end
        end

        WAKE_UP: begin
            seq_busy = 1'b1;
            if (seq_timer >= 8'h03 && pwr_stable && clk_stable) begin
                if (retention_ready) begin
                    next_state = ACTIVE;
                end else if (seq_timer >= 8'h0F) begin
                    next_state = ACTIVE;
                    error = 1'b1;
                end
            end
        end

        default: begin
            next_state = ACTIVE;
        end
    endcase
end

// ===================================================================
// Output Generation
// ===================================================================
always @(posedge clk or negedge reset_n) begin
    if (!reset_n) begin
        clk_gate_en <= 1'b0;
        pwr_gate_en <= 1'b0;
        retention_en <= 1'b0;
        retention_save <= 1'b0;
        retention_restore <= 1'b0;
        dvfs_ctrl <= 2'b11;
        reset_ctrl <= 1'b0;
        pwr_state <= 2'b00;
    end else begin
        // Default outputs (ACTIVE state)
        clk_gate_en <= 1'b0;
        pwr_gate_en <= 1'b0;
        retention_en <= 1'b0;
        retention_save <= 1'b0;
        retention_restore <= 1'b0;
        dvfs_ctrl <= 2'b11;
        reset_ctrl <= 1'b0;
        pwr_state <= 2'b00;

        case (curr_state)
            ACTIVE: begin
                pwr_state <= 2'b00;
                // All outputs already at default (active)
            end

            IDLE: begin
                pwr_state <= 2'b01;
                clk_gate_en <= 1'b1;
            end

            SLEEP: begin
                pwr_state <= 2'b10;
                clk_gate_en <= 1'b1;
                pwr_gate_en <= 1'b1;
                retention_en <= 1'b1;
                dvfs_ctrl <= 2'b01;
            end

            OFF: begin
                pwr_state <= 2'b11;
                clk_gate_en <= 1'b1;
                pwr_gate_en <= 1'b1;
                reset_ctrl <= 1'b1;
            end

            SLEEP_ENT: begin
                pwr_state <= 2'b10;
                retention_save <= (seq_timer < 8'h02);
                retention_en <= 1'b1;
            end

            OFF_ENT: begin
                pwr_state <= 2'b11;
                if (seq_timer < 8'h02) begin
                    retention_save <= 1'b1;
                end
            end

            WAKE_UP: begin
                pwr_state <= 2'b00;
                if (seq_timer >= 8'h01 && seq_timer < 8'h03) begin
                    retention_restore <= 1'b1;
                    retention_en <= 1'b1;
                end
                reset_ctrl <= (seq_timer < 8'h01);
            end

            default: begin
                pwr_state <= 2'b00;
            end
        endcase
    end
end

endmodule

Day_10/pmu_fsm/verify/tb_pmu_fsm.sv
// =======================================================================
//  PMU FSM Testbench - Enhanced Debugging
// =======================================================================
`timescale 1ns/1ps

module tb_pmu_fsm;
    reg clk;
    reg reset_n;

    // DUT inputs
    reg req_idle, req_sleep, req_off, wake_up;
    reg pwr_stable, clk_stable, retention_ready;

    // DUT outputs
    wire clk_gate_en, pwr_gate_en, reset_ctrl, retention_en;
    wire retention_save, retention_restore;
    wire [1:0] dvfs_ctrl, pwr_state;
    wire seq_busy, error;
    wire [2:0] curr_state;

    integer test_count, error_count;

    // Instantiate DUT
    pmu_fsm dut(
        .clk(clk),
        .reset_n(reset_n),
        .req_idle(req_idle), 
        .req_sleep(req_sleep), 
        .req_off(req_off), 
        .wake_up(wake_up),
        .pwr_stable(pwr_stable),
        .clk_stable(clk_stable),
        .retention_ready(retention_ready),
        .clk_gate_en(clk_gate_en),
        .pwr_gate_en(pwr_gate_en),
        .retention_en(retention_en),
        .retention_save(retention_save),
        .retention_restore(retention_restore),
        .dvfs_ctrl(dvfs_ctrl),
        .reset_ctrl(reset_ctrl), 
        .pwr_state(pwr_state),
        .seq_busy(seq_busy),
        .error(error)
    );

    assign curr_state = dut.curr_state;

    // Clock generation
    always #5 clk = ~clk;

    // Helper function to get state name
    function [80:0] get_state_name;
        input [2:0] state;
        case (state)
            3'b000: get_state_name = "ACTIVE";
            3'b001: get_state_name = "IDLE";
            3'b010: get_state_name = "SLEEP";
            3'b011: get_state_name = "OFF";
            3'b100: get_state_name = "SLEEP_ENT";
            3'b101: get_state_name = "OFF_ENT";
            3'b110: get_state_name = "WAKE_UP";
            default: get_state_name = "UNKNOWN";
        endcase
    endfunction

    // Reset task
    task reset_system;
        begin
            $display("[TASK] Applying reset...");
            reset_n = 0;
            req_idle = 0;
            req_sleep = 0;
            req_off = 0;
            wake_up = 0;
            pwr_stable = 1;
            clk_stable = 1;
            retention_ready = 1;
            repeat(5) @(posedge clk);
            reset_n = 1;
            repeat(2) @(posedge clk);
            $display("[TASK] Reset released. Current state: %s", get_state_name(curr_state));
        end
    endtask

    // Wait cycles with debug info
    task wait_cycles;
        input integer cycles;
        integer i;
        begin
            for (i = 0; i < cycles; i = i + 1) begin
                @(posedge clk);
                $display("  [Cycle %0d] State: %s, sync: idle=%b sleep=%b off=%b wake=%b", 
                         i, get_state_name(curr_state), 
                         dut.req_idle_sync, dut.req_sleep_sync, 
                         dut.req_off_sync, dut.wake_up_sync);
            end
        end
    endtask

    // State check task
    task check_state;
        input [2:0] expected_state;
        input [80:0] state_name;
        begin
            if (curr_state !== expected_state) begin
                $display("ERROR: Expected %s (0x%0h), got %s (0x%0h)", 
                        state_name, expected_state, get_state_name(curr_state), curr_state);
                error_count = error_count + 1;
            end else begin
                $display("PASS:  %s", state_name);
            end
            test_count = test_count + 1;
        end
    endtask

    // =======================================================================
    // Specific Debug Tests
    // =======================================================================

    task test_active_to_idle_debug;
        begin
            $display("\nDEBUG TEST: ACTIVE -> IDLE");
            reset_system();
            
            $display("Setting req_idle=1");
            req_idle = 1;
            
            // Wait for synchronization and state transition
            wait_cycles(4);
            
            req_idle = 0;
            check_state(3'b001, "IDLE");
            
            if (clk_gate_en !== 1'b1) begin
                $display("ERROR: clk_gate_en should be 1 in IDLE, got %b", clk_gate_en);
                error_count = error_count + 1;
            end else begin
                $display("PASS: clk_gate_en = 1 in IDLE");
            end
        end
    endtask

    task test_active_to_sleep_ent_debug;
        begin
            $display("\nDEBUG TEST: ACTIVE -> SLEEP_ENT");
            reset_system();
            
            $display("Setting req_sleep=1");
            req_sleep = 1;
            
            // Wait for synchronization and state transition
            wait_cycles(4);
            
            req_sleep = 0;
            check_state(3'b100, "SLEEP_ENT");
            
            if (seq_busy !== 1'b1) begin
                $display("ERROR: seq_busy should be 1 in SLEEP_ENT, got %b", seq_busy);
                error_count = error_count + 1;
            end else begin
                $display("PASS: seq_busy = 1 in SLEEP_ENT");
            end
            
            // Continue sequence
            $display("Continuing SLEEP_ENT sequence...");
            retention_ready = 1;
            wait_cycles(5);
            check_state(3'b010, "SLEEP");
        end
    endtask

    // =======================================================================
    // Main Test Sequence
    // =======================================================================

    initial begin
        // Initialize
        clk = 0;
        test_count = 0;
        error_count = 0;
        
        $display("Starting PMU FSM Debug Test");
        $display("===========================");
        
        // Run specific debug tests
        test_active_to_idle_debug();
        test_active_to_sleep_ent_debug();
        
        // Summary
        $display("\n=== TEST SUMMARY ===");
        $display("Tests run: %0d", test_count);
        $display("Errors:    %0d", error_count);
        
        if (error_count == 0) begin
            $display("*** ALL TESTS PASSED ***");
        end else begin
            $display("*** TESTS FAILED ***");
        end
        
        $finish;
    end

    // VCD dump for detailed debugging
    initial begin
        $dumpfile("pmu_fsm_debug.vcd");
        $dumpvars(0, tb_pmu_fsm);
    end

    // Timeout
    initial begin
        #50000;
        $display("Timeout: Simulation too long");
        $finish;
    end

endmodule

Day_6/verify/pmu_fsm_debug.vcd
$date
	Sun Oct  5 12:41:06 2025
$end
$version
	Icarus Verilog
$end
$timescale
	1ps
$end
$scope module tb_pmu_fsm $end
$var wire 3 ! curr_state [2:0] $end
$var wire 1 " seq_busy $end
$var wire 1 # retention_save $end
$var wire 1 $ retention_restore $end
$var wire 1 % retention_en $end
$var wire 1 & reset_ctrl $end
$var wire 2 ' pwr_state [1:0] $end
$var wire 1 ( pwr_gate_en $end
$var wire 1 ) error $end
$var wire 2 * dvfs_ctrl [1:0] $end
$var wire 1 + clk_gate_en $end
$var reg 1 , clk $end
$var reg 1 - clk_stable $end
$var reg 1 . pwr_stable $end
$var reg 1 / req_idle $end
$var reg 1 0 req_off $end
$var reg 1 1 req_sleep $end
$var reg 1 2 reset_n $end
$var reg 1 3 retention_ready $end
$var reg 1 4 wake_up $end
$var integer 32 5 error_count [31:0] $end
$var integer 32 6 test_count [31:0] $end
$scope function get_state_name $end
$var reg 3 7 state [2:0] $end
$upscope $end
$scope module dut $end
$var wire 1 , clk $end
$var wire 1 - clk_stable $end
$var wire 1 . pwr_stable $end
$var wire 1 / req_idle $end
$var wire 1 0 req_off $end
$var wire 1 1 req_sleep $end
$var wire 1 2 reset_n $end
$var wire 1 3 retention_ready $end
$var wire 1 4 wake_up $end
$var wire 1 8 wake_up_sync $end
$var wire 1 9 req_sleep_sync $end
$var wire 1 : req_off_sync $end
$var wire 1 ; req_idle_sync $end
$var reg 1 + clk_gate_en $end
$var reg 3 < curr_state [2:0] $end
$var reg 2 = dvfs_ctrl [1:0] $end
$var reg 1 ) error $end
$var reg 3 > next_state [2:0] $end
$var reg 1 ( pwr_gate_en $end
$var reg 2 ? pwr_state [1:0] $end
$var reg 1 & reset_ctrl $end
$var reg 1 % retention_en $end
$var reg 1 $ retention_restore $end
$var reg 1 # retention_save $end
$var reg 1 " seq_busy $end
$var reg 8 @ seq_timer [7:0] $end
$var reg 4 A sync_stage1 [3:0] $end
$var reg 4 B sync_stage2 [3:0] $end
$upscope $end
$scope task check_state $end
$var reg 3 C expected_state [2:0] $end
$var reg 81 D state_name [80:0] $end
$upscope $end
$scope task reset_system $end
$upscope $end
$scope task test_active_to_idle_debug $end
$upscope $end
$scope task test_active_to_sleep_ent_debug $end
$upscope $end
$scope task wait_cycles $end
$var integer 32 E cycles [31:0] $end
$var integer 32 F i [31:0] $end
$upscope $end
$upscope $end
$enddefinitions $end
#0
$dumpvars
bx F
bx E
bx D
bx C
b0 B
b0 A
b0 @
b0 ?
b0 >
b11 =
b0 <
0;
0:
09
08
bx 7
b0 6
b0 5
04
13
02
01
00
0/
1.
1-
0,
0+
b11 *
0)
0(
b0 '
0&
0%
0$
0#
0"
b0 !
$end
#5000
1,
#10000
0,
#15000
1,
#20000
0,
#25000
1,
#30000
0,
#35000
1,
#40000
0,
#45000
12
1,
#50000
0,
#55000
1,
#60000
0,
#65000
b1000 A
b0 F
b100 E
1/
b0 7
1,
#70000
0,
#75000
b1 >
1;
b1000 B
b1 F
1,
#80000
0,
#85000
b1 !
b1 <
b10 F
1,
#90000
0,
#95000
1+
b1 '
b1 ?
b11 F
b1 7
1,
#100000
0,
#105000
b0 >
0;
b0 '
b0 ?
0+
b0 !
b0 <
b0 B
b0 A
02
b1 6
b1001001010001000100110001000101 D
b1 C
0/
b100 F
1,
#110000
0,
#115000
1,
#120000
0,
#125000
1,
#130000
0,
#135000
1,
#140000
0,
#145000
1,
#150000
0,
#155000
12
1,
#160000
0,
#165000
1,
#170000
0,
#175000
b100 A
b0 F
11
b0 7
1,
#180000
0,
#185000
b100 >
19
b100 B
b1 F
1,
#190000
0,
#195000
1"
b100 !
b100 <
b10 F
1,
#200000
0,
#205000
1"
1%
1#
b10 '
b10 ?
b1 @
b11 F
b100 7
1,
#210000
0,
#215000
1"
b0 A
b10 @
b10 '
b10 ?
1#
1%
b101 E
b10 6
b10100110100110001000101010001010101000001011111010001010100111001010100 D
b100 C
01
b0 F
1,
#220000
0,
#225000
b10 >
1"
09
b10 '
b10 ?
0#
1%
b11 @
b0 B
b1 F
1,
#230000
0,
#235000
0"
b0 @
b10 !
b10 <
b10 '
b10 ?
1%
b10 F
1,
#240000
0,
#245000
b1 *
b1 =
1(
1+
b10 '
b10 ?
1%
b11 F
b10 7
1,
#250000
0,
#255000
b10 '
b10 ?
b1 *
b1 =
1%
1(
1+
b100 F
1,
#260000
0,
#265000
b10 '
b10 ?
b1 *
b1 =
1%
1(
1+
b11 6
b101001101001100010001010100010101010000 D
b10 C
b101 F
1,
